api_wrapper/__init__.py
api_wrapper/bigtime_api.py
api_wrapper/exceptions.py
api_wrapper/models.py
api_wrapper/rest_adapter.py
api_wrapper/utils.py
api_wrapper/endpoints/__init__.py
api_wrapper/endpoints/clients.py
api_wrapper/endpoints/expenses.py
api_wrapper/endpoints/invoices.py
api_wrapper/endpoints/payments.py
api_wrapper/endpoints/picklist.py
api_wrapper/endpoints/projects.py
api_wrapper/endpoints/reports.py
api_wrapper/endpoints/staff.py
api_wrapper/endpoints/tasks.py
api_wrapper/endpoints/time.py
api_wrapper/methods/__init__.py
api_wrapper/methods/create.py
api_wrapper/methods/delete.py
api_wrapper/methods/get.py
api_wrapper/methods/update.py
bigtime_api_python-0.0.2.dist-info/METADATA
bigtime_api_python-0.0.2.dist-info/WHEEL
bigtime_api_python-0.0.2.dist-info/licenses/LICENSE
bigtime_api_python-0.0.2.dist-info/RECORD
