Metadata-Version: 2.4
Name: bigtime-api-python
Version: 0.0.2
Summary: bigtime-api-python is an API wrapper for the BigTime API
Project-URL: Homepage, https://github.com/N3RM/bigtime-api-python
Project-URL: Issues, https://github.com/N3RM/bigtime-api-python/issues
Author-email: Noel Moyer III <moyer.noel@gmail.com>
License-Expression: GPL-3.0-or-later
License-File: LICENSE
Keywords: API Wrapper,BigTime
Classifier: Development Status :: 3 - Alpha
Classifier: Intended Audience :: Developers
Classifier: License :: OSI Approved :: GNU General Public License v3 or later (GPLv3+)
Classifier: Natural Language :: English
Classifier: Operating System :: OS Independent
Classifier: Programming Language :: Python :: 3
Requires-Python: >=3.13
